netjsonFlaskRest/__init__.py
netjsonFlaskRest/flaskRestAPI.py
netjson_rest-1.0.4.dist-info/METADATA
netjson_rest-1.0.4.dist-info/WHEEL
netjson_rest-1.0.4.dist-info/license.txt
netjson_rest-1.0.4.dist-info/top_level.txt
netjson_rest-1.0.4.dist-info/RECORD
