Metadata-Version: 2.1
Name: netjson-rest
Version: 1.0.4
Summary: Rest API to convert openwrt config to json and vice versa using flask
Home-page: https://github.com/umeshahp/netjson-rest
Author: Umesha HP
Author-email: hpu89@yahoo.com
License: GPLV3
Keywords: Rest API for netjson config
Platform: UNKNOWN
Classifier: Development Status :: 4 - Beta
Classifier: Intended Audience :: Developers
Classifier: Topic :: Internet
Classifier: Programming Language :: Python
Classifier: Programming Language :: Python :: 2
Classifier: Programming Language :: Python :: 2.6
Classifier: Programming Language :: Python :: 2.7
Classifier: Programming Language :: Python :: 3
Classifier: Programming Language :: Python :: 3.3
Classifier: Programming Language :: Python :: 3.4
Classifier: Programming Language :: Python :: 3.5
Classifier: Programming Language :: Python :: 3.6
Classifier: Programming Language :: Python :: 3.7
Requires-Dist: requests
Requires-Dist: netjsonconfig
Requires-Dist: flask
